RemoteHotKey/ActionManager.py
RemoteHotKey/ClientManager.py
RemoteHotKey/FlaskWebUpdateListener.py
RemoteHotKey/OneTimeEvent.py
RemoteHotKey/State.py
RemoteHotKey/UpdateListener.py
RemoteHotKey/__init__.py
RemoteHotKey/definitions.py
RemoteHotKey/Utility/ActionPerformer.py
RemoteHotKey/Utility/ActionPerformer_Pynput.py
RemoteHotKey/Utility/KeyboardMouseActionPerformer.py
RemoteHotKey/Utility/__init__.py
RemoteHotKey/WebUI/Button.py
RemoteHotKey/WebUI/GenericButton.py
RemoteHotKey/WebUI/Slider.py
RemoteHotKey/WebUI/Text.py
RemoteHotKey/WebUI/UIElement.py
RemoteHotKey/WebUI/UITemplate.py
RemoteHotKey/WebUI/__init__.py
RemoteHotKey/WebUI/templates/__init__.py
RemoteHotKey/WebUI/templates/controlpadFlask.html
remotehotkey-0.1.8.dist-info/METADATA
remotehotkey-0.1.8.dist-info/WHEEL
remotehotkey-0.1.8.dist-info/top_level.txt
remotehotkey-0.1.8.dist-info/RECORD
